simpletemplate/__init__.py
simpletemplate-0.0.1b1.dist-info/METADATA
simpletemplate-0.0.1b1.dist-info/RECORD
simpletemplate-0.0.1b1.dist-info/WHEEL
simpletemplate-0.0.1b1.dist-info/top_level.txt
