Metadata-Version: 2.1
Name: simpletemplate
Version: 0.0.1b1
Summary: 简单灵活的代码生成模板引擎
Home-page: https://github.com/weixinfree/template
Author: WangWei
Author-email: 2317073226@qq.com
License: UNKNOWN
Platform: UNKNOWN
Classifier: Programming Language :: Python :: 3.7
Classifier: License :: OSI Approved :: MIT License
Classifier: Operating System :: OS Independent
